printfactory/__init__.py
printfactory/print_tool.py
printfactory/print_tools/__init__.py
printfactory/print_tools/adobe.py
printfactory/printer.py
printfactory-0.1.2a0.dist-info/LICENSE
printfactory-0.1.2a0.dist-info/WHEEL
printfactory-0.1.2a0.dist-info/METADATA
printfactory-0.1.2a0.dist-info/RECORD
