Metadata-Version: 2.1
Name: printfactory
Version: 0.1.2a0
Summary: Print PDF files to a local installed printer using a print tool
Home-page: https://github.com/dl6nm/printfactory
License: MIT
Keywords: print,pdf,files,printfactory
Author: dl6nm
Author-email: mail@dl6nm.de
Requires-Python: >=3.8,<4.0
Classifier: License :: OSI Approved :: MIT License
Classifier: Operating System :: MacOS
Classifier: Operating System :: Microsoft :: Windows
Classifier: Programming Language :: Python :: 3
Classifier: Programming Language :: Python :: 3.8
Classifier: Programming Language :: Python :: 3.9
Classifier: Topic :: Printing
Requires-Dist: pydantic (>=1.7.3,<2.0.0)
Project-URL: Changelog, https://github.com/dl6nm/printfactory/blob/main/CHANGELOG.md
Project-URL: Issue tracker, https://github.com/dl6nm/printfactory/issues
Project-URL: Repository, https://github.com/dl6nm/printfactory
